boolevard/__init__.py
boolevard/core.py
boolevard/perturbations.py
boolevard/transduction.py
boolevard/utils.py
boolevard-0.1.1.dist-info/licenses/LICENSE
boolevard-0.1.1.dist-info/METADATA
boolevard-0.1.1.dist-info/WHEEL
boolevard-0.1.1.dist-info/top_level.txt
boolevard-0.1.1.dist-info/RECORD
