Metadata-Version: 2.4
Name: boolevard
Version: 0.1.1
Summary: BooLEVARD: Boolean Logical Evaluation of Activation and Represion in Directed pathways
Home-page: https://github.com/farinasm/boolevard
Author: Marco Fariñas Fernandez
Author-email: marco.farinas@gmail.com
Classifier: Programming Language :: Python :: 3
Classifier: License :: OSI Approved :: MIT License
Classifier: Operating System :: OS Independent
License-File: LICENSE
Requires-Dist: pyeda==0.26.0
Requires-Dist: mpbn
Requires-Dist: colomoto_jupyter
Requires-Dist: pandas
Dynamic: author
Dynamic: author-email
Dynamic: classifier
Dynamic: description
Dynamic: description-content-type
Dynamic: home-page
Dynamic: license-file
Dynamic: requires-dist
Dynamic: summary
